README.md
setup.py
bitrise/__init__.py
bitrise/exceptions.py
bitrise.egg-info/PKG-INFO
bitrise.egg-info/SOURCES.txt
bitrise.egg-info/dependency_links.txt
bitrise.egg-info/requires.txt
bitrise.egg-info/top_level.txt
bitrise/client/__init__.py
bitrise/client/client.py
bitrise/services/__init__.py
bitrise/services/apps.py
bitrise/services/bitrise.py
bitrise/services/bitrise_payload.py
bitrise/services/builds.py