Metadata-Version: 1.0
Name: bitrise
Version: 1.0.2
Summary: Python bindings for Bitrise REST API
Home-page: https://github.com/brandonblair/bitrise
Author: Brandon Blair
Author-email: cbrandon.blair@gmail.com
License: UNKNOWN
Platform: UNKNOWN
